inference_client/__init__.py
inference_client/__version__.py
inference_client/client.py
inference_client/config.py
inference_client/helper.py
inference_client/logging.py
inference_client/model.py
inference_client/tasks/caption.py
inference_client/tasks/encode.py
inference_client/tasks/generate.py
inference_client/tasks/helper.py
inference_client/tasks/rank.py
inference_client/tasks/upscale.py
inference_client/tasks/vqa.py
inference_client-0.0.8.dist-info/LICENSE
inference_client-0.0.8.dist-info/METADATA
inference_client-0.0.8.dist-info/WHEEL
inference_client-0.0.8.dist-info/RECORD
