Metadata-Version: 2.1
Name: inference-client
Version: 0.0.8
Summary: Python Client for Jina Inference API
Home-page: https://inference-api.jina.ai
License: Apache-2.0
Keywords: jina,inference,api,client
Author: Jina AI
Author-email: hello@jina.ai
Requires-Python: >=3.8,<4.0.0
Classifier: License :: OSI Approved :: Apache Software License
Classifier: Programming Language :: Python :: 3
Classifier: Programming Language :: Python :: 3.8
Classifier: Programming Language :: Python :: 3.9
Classifier: Programming Language :: Python :: 3.10
Classifier: Programming Language :: Python :: 3.11
Provides-Extra: pytorch
Requires-Dist: docarray (>=0.21.0,<0.22.0)
Requires-Dist: jina (>=3.14.0,<4.0.0)
Requires-Dist: jina-hubble-sdk (>=0.34.0)
Requires-Dist: pillow (>=9.4.0,<10.0.0)
Requires-Dist: pydantic (>=1.10.7,<2.0.0)
Requires-Dist: rich (>=13.3.0,<14.0.0)
Requires-Dist: torch (>=1.10.0) ; extra == "pytorch"
Project-URL: Repository, https://github.com/jina-ai/inference-client
